LICENSE
README.md
setup.py
src/yupeeee_pytools/__init__.py
src/yupeeee_pytools.egg-info/PKG-INFO
src/yupeeee_pytools.egg-info/SOURCES.txt
src/yupeeee_pytools.egg-info/dependency_links.txt
src/yupeeee_pytools.egg-info/requires.txt
src/yupeeee_pytools.egg-info/top_level.txt
src/yupeeee_pytools/attacks/__init__.py
src/yupeeee_pytools/attacks/ifgsm.py
src/yupeeee_pytools/datasets/__init__.py
src/yupeeee_pytools/datasets/base.py
src/yupeeee_pytools/datasets/classification.py
src/yupeeee_pytools/datasets/config.py
src/yupeeee_pytools/datasets/normalize.py
src/yupeeee_pytools/models/__init__.py
src/yupeeee_pytools/models/classification/__init__.py
src/yupeeee_pytools/models/classification/base.py
src/yupeeee_pytools/models/classification/config.py
src/yupeeee_pytools/models/classification/model.py
src/yupeeee_pytools/models/classification/preprocess.py
src/yupeeee_pytools/models/classification/nets/__init__.py
src/yupeeee_pytools/models/classification/nets/deit.py
src/yupeeee_pytools/models/classification/nets/mixer.py
src/yupeeee_pytools/models/classification/nets/poolformer.py
src/yupeeee_pytools/models/classification/nets/pvt.py
src/yupeeee_pytools/models/replace/__init__.py
src/yupeeee_pytools/models/replace/activation.py
src/yupeeee_pytools/models/replace/base.py
src/yupeeee_pytools/models/replace/common.py
src/yupeeee_pytools/models/replace/config.py
src/yupeeee_pytools/models/replace/normalization.py
src/yupeeee_pytools/tools/__init__.py
src/yupeeee_pytools/tools/dictools.py
src/yupeeee_pytools/tools/imgtools.py
src/yupeeee_pytools/tools/linalgtools.py
src/yupeeee_pytools/tools/listools.py
src/yupeeee_pytools/tools/misctools.py
src/yupeeee_pytools/tools/pathtools.py
src/yupeeee_pytools/tools/randtools.py
src/yupeeee_pytools/train/__init__.py
src/yupeeee_pytools/train/base.py
src/yupeeee_pytools/train/criterion.py
src/yupeeee_pytools/train/dataloader.py
src/yupeeee_pytools/train/lr_scheduler.py
src/yupeeee_pytools/train/lr_warmup.py
src/yupeeee_pytools/train/optimizer.py
src/yupeeee_pytools/train/trainer.py
src/yupeeee_pytools/travel/__init__.py
src/yupeeee_pytools/travel/common.py
src/yupeeee_pytools/travel/config.py
src/yupeeee_pytools/travel/direction.py
