Metadata-Version: 2.1
Name: yupeeee-pytools
Version: 0.1.21
Home-page: https://github.com/yupeeee/PyTools
Author: Juyeop Kim
Author-email: juyeopkim@yonsei.ac.kr
License: MIT
License-File: LICENSE
